<?xml version="1.0" encoding="UTF-8"?>
<con:resource name="Projects" path="/rest-api/service/api/v1/projects/11874/requirements/3" id="23ef8c1e-bd03-407e-9dac-bad9a8d411b3" xmlns:xsi="http://www.w3.org/2001/XMLSchema-instance" xmlns:con="http://eviware.com/soapui/config"><con:settings><con:setting id="23ef8c1e-bd03-407e-9dac-bad9a8d411b3fileName">Projects</con:setting></con:settings><con:parameters/><con:method name="Projects" id="6983c504-1bca-4544-944e-09b588d4ac61" method="GET"><con:settings/><con:parameters/><con:representation type="FAULT"><con:mediaType xsi:nil="true"/><con:status>401</con:status><con:params/><con:element>data</con:element></con:representation><con:representation type="FAULT"><con:mediaType xsi:nil="true"/><con:status>401</con:status><con:params/><con:element>data</con:element></con:representation><con:request name="Request 1" id="6cd8d38f-f266-4826-973c-a456747d5e47" mediaType="application/json"><con:settings><con:setting id="com.eviware.soapui.impl.wsdl.WsdlRequest@request-headers">&lt;xml-fragment/></con:setting></con:settings><con:endpoint>http://sv-alm</con:endpoint><con:request/><con:originalUri>http://sv-alm/rest-api/service/api/v1/projects/</con:originalUri><con:credentials><con:selectedAuthProfile>No Authorization</con:selectedAuthProfile><con:authType>No Authorization</con:authType></con:credentials><con:jmsConfig JMSDeliveryMode="PERSISTENT"/><con:parameters/></con:request></con:method></con:resource>